<annotation>
	<folder>JPEGImages</folder>
	<filename>9419.jpg</filename>
	<path>D:\JPEGImages\9419.jpg</path>
	<source>
		<database>Unknown</database>
	</source>
	<size>
		<width>640</width>
		<height>480</height>
		<depth>3</depth>
	</size>
	<segmented>0</segmented>
	<object>
		<name>multimeter</name>
		<pose>Unspecified</pose>
		<truncated>0</truncated>
		<difficult>0</difficult>
		<bndbox>
			<xmin>159</xmin>
			<ymin>116</ymin>
			<xmax>512</xmax>
			<ymax>312</ymax>
		</bndbox>
	</object>
	<object>
		<name>screw hole</name>
		<pose>Unspecified</pose>
		<truncated>0</truncated>
		<difficult>0</difficult>
		<bndbox>
			<xmin>473</xmin>
			<ymin>148</ymin>
			<xmax>490</xmax>
			<ymax>165</ymax>
		</bndbox>
	</object>
	<object>
		<name>screw hole</name>
		<pose>Unspecified</pose>
		<truncated>0</truncated>
		<difficult>0</difficult>
		<bndbox>
			<xmin>472</xmin>
			<ymin>258</ymin>
			<xmax>488</xmax>
			<ymax>273</ymax>
		</bndbox>
	</object>
</annotation>
